{
  "0": {
    "name": "-",
    "face": "表情",
    "text": "セリフ内容"
  },
  "1": {
    "name": null,
    "face": null,
    "text": "●場面：ルクレア村初訪問"
  },
  "2": {
    "name": "-",
    "face": "-",
    "text": null
  },
  "3": {
    "name": null,
    "face": null,
    "text": null
  },
  "4": {
    "name": "ソル",
    "face": "普通2",
    "text": "「おおおおお……これがルクレア村………\n　せんせい以外の人がいっぱいいる……すげえ……」"
  },
  "5": {
    "name": "ソル",
    "face": "喜2",
    "text": "「なんか賑やかでいいなぁー……\n　すごく新鮮な気分ですね！」"
  },
  "6": {
    "name": null,
    "face": null,
    "text": null
  },
  "7": {
    "name": "ソル",
    "face": "喜3",
    "text": "「噴水！！！！水車！！！！馬車！！！！！\n　おおおおおおおお…………文明の兆し………」"
  },
  "8": {
    "name": "村人",
    "face": null,
    "text": "「………？？」"
  },
  "9": {
    "name": "村人",
    "face": null,
    "text": "「……？？………？？？」"
  },
  "10": {
    "name": "ソル",
    "face": "喜2",
    "text": "「えへへー」"
  },
  "11": {
    "name": null,
    "face": null,
    "text": null
  },
  "12": {
    "name": "ナレーション",
    "face": null,
    "text": "ソルが村の通りを歩くと、村人達は皆驚いたように振り返る。\n金色の竜の尾を持つ美少女、それもまるで吟遊詩人が物語る\n人魚姫の如き半裸となれば目立たぬ筈もなかった。"
  },
  "13": {
    "name": "ナレーション",
    "face": null,
    "text": "そして、通り掛かる赤髪の冒険者もまた\nその姿を鮮明に覚えていたのだった。"
  },
  "14": {
    "name": null,
    "face": null,
    "text": null
  },
  "15": {
    "name": "エリック",
    "face": "普通1",
    "text": "「ん………あれ？　もしかして……」"
  },
  "16": {
    "name": "ソル",
    "face": "普通3",
    "text": "「ほい？？？」"
  },
  "17": {
    "name": "エリック",
    "face": "喜2",
    "text": "「あー！あの時の助けてくれた金竜の子！！\n　探してたんだから！」"
  },
  "18": {
    "name": "ソル",
    "face": "喜1",
    "text": "「あー！あの時のおねえさん！！」"
  },
  "19": {
    "name": null,
    "face": null,
    "text": null
  },
  "20": {
    "name": null,
    "face": null,
    "text": "暗転"
  },
  "21": {
    "name": null,
    "face": null,
    "text": null
  },
  "22": {
    "name": null,
    "face": null,
    "text": null
  },
  "23": {
    "name": "エリック",
    "face": "普通1",
    "text": "「はー、成程ねえ。噂には聞いていたけど……\n　あのエニ先生に育てられてた金竜ってのがキミだったんだね」"
  },
  "24": {
    "name": "エリック",
    "face": "喜3",
    "text": "「お礼言えてなかったよね。あの時はホントにありがと。\n　あたしはエリック。ここいらで活動してる冒険者」"
  },
  "25": {
    "name": "ソル",
    "face": "喜2",
    "text": "「いえいえー」"
  },
  "26": {
    "name": "エリック",
    "face": "喜2",
    "text": "「よっし、恩返しって訳でもないけどさ、せっかくだし\n　これもなにかの縁ってことで、あたしもソルに付き合うね！」"
  },
  "27": {
    "name": "ソル",
    "face": "普通2",
    "text": "「え、いいんですか！？」"
  },
  "28": {
    "name": "エリック",
    "face": "普通1",
    "text": "「エニ先生にも、『もしソルを見かけたら手伝って上げて欲しい』\n　って頼まれてるしね！冒険者の集まる酒場を案内したげる！」"
  },
  "29": {
    "name": "エリック",
    "face": "喜1",
    "text": "「『首なし美人』亭って言うんだけど、そこをたまり場にしてるんだ。\n　仲間を探してるってんなら、そこが一番かな」"
  },
  "30": {
    "name": "ソル",
    "face": "喜1",
    "text": "「おおー、なんかすごくそれっぽい！！\n　……なんで首がないのに美人ってわかるんでしょうね？？」"
  },
  "31": {
    "name": null,
    "face": null,
    "text": null
  },
  "32": {
    "name": null,
    "face": null,
    "text": "終了"
  },
  "33": {
    "name": null,
    "face": null,
    "text": null
  },
  "34": {
    "name": null,
    "face": null,
    "text": null
  },
  "35": {
    "name": null,
    "face": null,
    "text": null
  },
  "36": {
    "name": null,
    "face": null,
    "text": null
  }
}