{
  "0": {
    "name": "-",
    "face": "表情",
    "text": "セリフ内容"
  },
  "1": {
    "name": null,
    "face": null,
    "text": "●場面："
  },
  "2": {
    "name": "-",
    "face": "-",
    "text": null
  },
  "3": {
    "name": null,
    "face": null,
    "text": null
  },
  "4": {
    "name": null,
    "face": null,
    "text": null
  },
  "5": {
    "name": "ナレーション",
    "face": null,
    "text": "薄暗い宿の一室に、複数の男女の吐息が響き渡る。\nランプの明かりが、その淫猥な儀式を照らし\n彼らの影を床に落とす。"
  },
  "6": {
    "name": "ナレーション",
    "face": null,
    "text": "二人の女性が、ベッドの上でそれぞれ別の男に抱かれている。\n既に二人共うっすらと汗に塗れ、事が始まってからしばらく\n経ったと見える。"
  },
  "7": {
    "name": null,
    "face": null,
    "text": null
  },
  "8": {
    "name": "エニ先生",
    "face": null,
    "text": "「んっ、うぅっ、んっ……ふぅ……んっ……\n　まったく……ドラゴン、カインド、とは言え……っ……」"
  },
  "9": {
    "name": "エリック",
    "face": null,
    "text": "「ふ、あぅっ、く…ぅ……んっ……\n　諦めなって、先生……っ、こういう、もの、だから……っ」"
  },
  "10": {
    "name": "男",
    "face": null,
    "text": "「そうそう、こうなったら愉しんだ方がいいぜ、先生」"
  },
  "11": {
    "name": null,
    "face": null,
    "text": null
  },
  "12": {
    "name": "ナレーション",
    "face": null,
    "text": "未だに文句を言いながらも、されるがまま犯される先生。\n否定の言葉とは裏腹に、声には官能の色が強く滲み出ていた。"
  },
  "13": {
    "name": null,
    "face": null,
    "text": null
  },
  "14": {
    "name": "エニ先生",
    "face": null,
    "text": "「くぅ、んんんっ、んふぅっ、あ、あぅ……っっ……んんっ……！」"
  },
  "15": {
    "name": "男",
    "face": null,
    "text": "「へ、ほら、先生だってもう大分感じてるじゃない？\n　こんなに声まであげちゃってさ……」"
  },
  "16": {
    "name": "エニ先生",
    "face": null,
    "text": "「く、ぅ、んんっ……別に、感じて、いる訳、では……\n　んんんっっ………！」"
  },
  "17": {
    "name": "男",
    "face": null,
    "text": "「そう言って、随分ご無沙汰で持て余してたんじゃないの？\n　もう涎ダラッダラだよ？」"
  },
  "18": {
    "name": "エニ先生",
    "face": null,
    "text": "「……違い、ます………私は、そんな………ふ、ぅっ……\n　ん……ぅっ、持て余して、など………」"
  },
  "19": {
    "name": "エニ先生",
    "face": null,
    "text": "「あぅ…あ、あっ……いい、激し……っ……\n　んぅぅっ……！あ、ふぁ……っ…」"
  },
  "20": {
    "name": null,
    "face": null,
    "text": null
  },
  "21": {
    "name": "男2",
    "face": null,
    "text": "「エリックちゃんッ！へへ、エリックちゃんッ……！！」"
  },
  "22": {
    "name": "エリック",
    "face": null,
    "text": "「みんな、がっつき、すぎだって………\n　そん、な、慌てなく……ても……する、からさ……\n　あたしも、そんな、嫌いじゃ、ないし…さ………」"
  },
  "23": {
    "name": "男2",
    "face": null,
    "text": "「そんな事、言ってもよ……！\n　我慢できるわけ、ねえだろ……！」"
  },
  "24": {
    "name": "エリック",
    "face": null,
    "text": "「あ、あっ、ふ、んんんっ……！く………ぅ………\n　ちょ、っと……それ、は、あぁっ……！あ、ぅ……んっ…」"
  },
  "25": {
    "name": "エリック",
    "face": null,
    "text": "「あ、いい、それ、そこ、スゴく、好き、いいっ……！！\n　もっと、そこ、あ、あぅんっ、あああっ……！！」"
  },
  "26": {
    "name": null,
    "face": null,
    "text": null
  },
  "27": {
    "name": "エニ先生",
    "face": null,
    "text": "「んんんぅぅっ……！！、く、ぅぅぅぅ………！！」"
  },
  "28": {
    "name": "エリック",
    "face": null,
    "text": "「んっ、へへ、先生、も、だいぶ、良くなってきた、\n　みたいだね……ふ、あ、ぅ、あたしも、もう、\n　イキそ………」"
  },
  "29": {
    "name": "男",
    "face": null,
    "text": "「俺、もう、射精ちまうっ…！先生ェっ……！\n　膣内、出して、いいよね…！？」"
  },
  "30": {
    "name": "男2",
    "face": null,
    "text": "「く、俺もだ、エリック…！出すぞ、膣内、出すぞ！」"
  },
  "31": {
    "name": "エリック",
    "face": null,
    "text": "「いい、よ、出して、思いっきり、出して……！\n　好きに、して、いっぱい、んっ、ああああぁぁぁ……っ！！」"
  },
  "32": {
    "name": "エニ先生",
    "face": null,
    "text": "「射精して、射精して、ください……、好きに……！\n　んっ、あ、あ、あ、あぁぁっ……」"
  },
  "33": {
    "name": "エニ先生",
    "face": null,
    "text": "「んんんんんっっっっ……！！！」"
  },
  "34": {
    "name": null,
    "face": null,
    "text": null
  },
  "35": {
    "name": null,
    "face": null,
    "text": null
  },
  "36": {
    "name": null,
    "face": null,
    "text": null
  },
  "37": {
    "name": "エニ先生",
    "face": null,
    "text": "「ふぅ………ふぅ………くっ…………\n　……私、と、したことが………」"
  },
  "38": {
    "name": null,
    "face": null,
    "text": null
  },
  "39": {
    "name": "エリック",
    "face": null,
    "text": "「これで、終わりって、訳じゃないから、\n　も少し……頑張ろうね、先生」"
  },
  "40": {
    "name": "エニ先生",
    "face": null,
    "text": "「…………え？」"
  },
  "41": {
    "name": null,
    "face": null,
    "text": null
  },
  "42": {
    "name": "ナレーション",
    "face": null,
    "text": "先生がふと横を見れば、まだ彼女らを抱いていない\n手持ち無沙汰だった男たちが、今まさに\n襲いかからんとしていた。彼女らの乱れた姿を見て、\n既に股間は臨戦態勢に入っている。"
  },
  "43": {
    "name": null,
    "face": null,
    "text": null
  },
  "44": {
    "name": "エニ先生",
    "face": null,
    "text": "「え、あの、もう少し、その………んぅぅっ………！！！」"
  },
  "45": {
    "name": null,
    "face": null,
    "text": null
  },
  "46": {
    "name": "ナレーション",
    "face": null,
    "text": "エニ先生とエリックの姿は、また覆いかぶさる男達に隠れて\n見えなくなる。\n夜が空けるまで、開放されそうにはなかった……"
  },
  "47": {
    "name": null,
    "face": null,
    "text": "終了"
  },
  "48": {
    "name": null,
    "face": null,
    "text": null
  },
  "49": {
    "name": null,
    "face": null,
    "text": null
  },
  "50": {
    "name": null,
    "face": null,
    "text": null
  },
  "51": {
    "name": null,
    "face": null,
    "text": null
  },
  "52": {
    "name": null,
    "face": null,
    "text": null
  },
  "53": {
    "name": null,
    "face": null,
    "text": null
  },
  "54": {
    "name": null,
    "face": null,
    "text": null
  },
  "55": {
    "name": null,
    "face": null,
    "text": null
  },
  "56": {
    "name": null,
    "face": null,
    "text": null
  },
  "57": {
    "name": null,
    "face": null,
    "text": null
  },
  "58": {
    "name": null,
    "face": null,
    "text": null
  },
  "59": {
    "name": null,
    "face": null,
    "text": null
  },
  "60": {
    "name": null,
    "face": null,
    "text": null
  },
  "61": {
    "name": null,
    "face": null,
    "text": null
  },
  "62": {
    "name": null,
    "face": null,
    "text": null
  },
  "63": {
    "name": null,
    "face": null,
    "text": null
  },
  "64": {
    "name": null,
    "face": null,
    "text": null
  },
  "65": {
    "name": null,
    "face": null,
    "text": null
  },
  "66": {
    "name": null,
    "face": null,
    "text": null
  },
  "67": {
    "name": null,
    "face": null,
    "text": null
  },
  "68": {
    "name": null,
    "face": null,
    "text": null
  }
}